{
	"configuration": {
		"catalog": {
			"product_video": {
				"youtube_api_key": "AIzaSyB-WIL0GOj7vNdC8vgx5cdkV7FDl7D9oYs"
			}
		},
		"cataloginventory": {
			"source_selection_distance_based_google": {
				"api_key": "AIzaSyDFHxudRjZwPIbrY8hsrYFT4ruhNodFID0"
			}
		},
		"google": {
			"analytics": {
				"account": "",
				"container_id": "GTM-TT94LL"
			}
		},
		"payment": {
			"braintree": {
				"merchant_account_id": "magento",
				"merchant_id": "zkw2ctrkj75ndvkc",
				"public_key": "encrypt(sn6xgt8pqv8868pq)",
				"private_key": "encrypt(ad7807895eae5bd5a3cc913005eaefe8)",
				"sandbox_merchant_id": "3thxv4w4xhnkxzt5",
				"sandbox_public_key": "encrypt(n2bt4844t6xrt56x)",
				"sandbox_private_key": "encrypt(e6c98fd99fe699d4169475fef026d5b9)"
			},
			"paypal": {
				"general": {
					"business_account": "keith.bentrup-facilitator@gmail.com"
				},
				"wpp": {
					"api_username": "encrypt(keith.bentrup-facilitator_api1.gmail.com)",
					"api_password": "encrypt(U8QZ7GTBL9ZLVVKR)",
					"api_signature": "encrypt(AFcWxV21C7fd0v3bYYYRCpSSRl31AUZX6JF3NxAVVo8FbodrI5vv7)"
				}
			},
			"paypal_express": {
				"merchant_id": "87GXT6JMXY534"
			}
		}
	}
}
